dxx/__init__.py
dxx/dxxconv.py
dxx/filelib.py
dxx/len_file_dxx.py
dxx-0.1.3.dist-info/LICENSE.txt
dxx-0.1.3.dist-info/METADATA
dxx-0.1.3.dist-info/WHEEL
dxx-0.1.3.dist-info/entry_points.txt
dxx-0.1.3.dist-info/top_level.txt
dxx-0.1.3.dist-info/RECORD
