Metadata-Version: 2.1
Name: dxx
Version: 0.1.3
Summary: dxx is a library for io and converting audio files with a .DXX extension.
Home-page: https://github.com/tetsuzawa/dxx-py
Author: Tetsu Takizawa
Author-email: tetsu.varmos@gmail.com
License: UNKNOWN
Platform: UNKNOWN
Requires-Dist: numpy (==1.19.4)
Requires-Dist: SoundFile (==0.10.3.post1)
